README.md
setup.py
pyrevive/__init__.py
pyrevive.egg-info/PKG-INFO
pyrevive.egg-info/SOURCES.txt
pyrevive.egg-info/dependency_links.txt
pyrevive.egg-info/not-zip-safe
pyrevive.egg-info/requires.txt
pyrevive.egg-info/top_level.txt