Metadata-Version: 2.1
Name: pyrevive
Version: 0.0.6
Summary: Revive Hardware Restarter API Library
Home-page: https://github.com/RevolutionRigs/pyrevive
Author: Revolution Rigs
Author-email: nathan@revolutionrigs.com
License: GNU v3.0
Platform: UNKNOWN
